{
    "directions": [
        "Place frozen berries, almond milk, banana, and acai pulp in a blender; blend until smooth. Pour into 2 bowls and top with granola, mango, strawberries, and kiwi slices. Drizzle with agave syrup."
    ],
    "image": "https://imagesvc.meredithcorp.io/v3/mm/image?q=85&c=sc&poi=face&w=2228&h=1114&url=https%3A%2F%2Fimages.media-allrecipes.com%2Fuserphotos%2F5287316.jpg",
    "ingredients": [
        "1\u2009\u00bd cups mixed frozen berries",
        "1\u2009\u00bc cups unsweetened almond milk",
        "1  banana",
        "4 ounces frozen unsweetened acai pulp (such as Sambazon\u00ae)",
        "\u00bd cup granola",
        "\u00bd cup diced mango",
        "\u00bd cup sliced fresh strawberries",
        "1  kiwi, peeled and sliced",
        "2 tablespoons agave syrup"
    ],
    "language": "en-US",
    "source": "www.allrecipes.com",
    "tags": [],
    "title": "Acai Rainbow Smoothie Bowl for 2",
    "url": "https://www.allrecipes.com/recipe/261317/acai-rainbow-smoothie-bowl-for-2/"
}