{
    "directions": [
        "Heat the olive oil in a medium skillet over medium heat, and cook the onion until tender. Mix in the black-eyed peas, vegetable stock, jalapeno, garlic, and lime juice. Season with salt and pepper to taste, and continue cooking  until heated through. Wrap the mixture in the tortillas to serve."
    ],
    "image": "https://imagesvc.meredithcorp.io/v3/mm/image?q=85&c=sc&poi=face&w=4608&h=2304&url=https%3A%2F%2Fimages.media-allrecipes.com%2Fuserphotos%2F1098126.jpg",
    "ingredients": [
        "1 tablespoon olive oil",
        "\u00bc cup finely chopped onion",
        "1 (15.5 ounce) can black-eyed peas, drained",
        "\u00bd cup vegetable stock",
        "1  fresh jalapeno pepper, chopped",
        "1 clove garlic, minced",
        "1 tablespoon fresh lime juice",
        "salt and pepper to taste",
        "4 (12 inch) flour tortillas"
    ],
    "language": "en-US",
    "source": "www.allrecipes.com",
    "tags": [],
    "title": "Black-Eyed Peas and Tortillas",
    "url": "https://www.allrecipes.com/recipe/47898/black-eyed-peas-and-tortillas/"
}