{
    "directions": [
        "Combine the potatoes, spinach, carrots, turnips, garlic, and lentils in a slow cooker. Pour enough water over the mixture to cover.",
        "In a bowl, stir the fresh basil, chili powder, cinnamon, dried basil, paprika, turmeric, cayenne pepper, ground ginger, sea salt, and black pepper; stir into the slow cooker.",
        "Cover the cooker, and cook on High for 8 hours."
    ],
    "image": "https://www.allrecipes.com/img/misc/og-default.png",
    "ingredients": [
        "3  yellow potatoes (such as Klondike Goldust\u00ae), cubed",
        "1 (10 ounce) package frozen chopped spinach, thawed and drained",
        "2 large carrots, chopped",
        "2  turnips, diced",
        "3 cloves garlic, minced",
        "\u00be cup dry lentils",
        "water, or amount to cover",
        "\u00bc teaspoon chopped fresh basil",
        "1 teaspoon chili powder",
        "\u00bc teaspoon ground cinnamon",
        "\u00bc teaspoon dried basil",
        "\u00bc teaspoon paprika",
        "\u215b teaspoon ground turmeric",
        "\u215b teaspoon cayenne pepper",
        "\u215b teaspoon ground ginger",
        "sea salt and ground black pepper to taste"
    ],
    "language": "en-US",
    "source": "www.allrecipes.com",
    "tags": [],
    "title": "Cindy's Snappy Sensational Superfood Soup",
    "url": "https://www.allrecipes.com/recipe/219160/cindys-snappy-sensational-superfood-soup/"
}