{
    "directions": [
        "In a saucepan, combine the coconut milk, water and black-eyed peas. Stir in rice. Bring to a boil, cover and reduce heat to low. Simmer until rice has absorbed all of the liquid, about 40 minutes."
    ],
    "image": "https://imagesvc.meredithcorp.io/v3/mm/image?q=85&c=sc&poi=face&w=1280&h=640&url=https%3A%2F%2Fimages.media-allrecipes.com%2Fuserphotos%2F1040344.jpg",
    "ingredients": [
        "\u00bd cup coconut milk",
        "2 cups water",
        "1 (15.5 ounce) can black-eyed peas, drained",
        "1 cup brown rice"
    ],
    "language": "en-US",
    "source": "www.allrecipes.com",
    "tags": [],
    "title": "Easy Coconut Rice and Black-Eyed Peas",
    "url": "https://www.allrecipes.com/recipe/153469/easy-coconut-rice-and-black-eyed-peas/"
}