{
    "directions": [
        "Place the garbanzo beans, tahini, lemon juice, salt and garlic in a blender or food processor. Blend until smooth. Transfer mixture to a serving bowl.",
        "Drizzle olive oil over the garbanzo bean mixture. Sprinkle with paprika and parsley."
    ],
    "image": "https://imagesvc.meredithcorp.io/v3/mm/image?q=85&c=sc&poi=face&w=2448&h=1224&url=https%3A%2F%2Fimages.media-allrecipes.com%2Fuserphotos%2F4477057.jpg",
    "ingredients": [
        "2 cups canned garbanzo beans, drained",
        "\u2153 cup tahini",
        "\u00bc cup lemon juice",
        "1 teaspoon salt",
        "2 cloves garlic, halved",
        "1 tablespoon olive oil",
        "1 pinch paprika",
        "1 teaspoon minced fresh parsley"
    ],
    "language": "en-US",
    "source": "www.allrecipes.com",
    "tags": [],
    "title": "Hummus III | Allrecipes",
    "url": "https://www.allrecipes.com/recipe/14830/hummus-iii/"
}