{
    "directions": [
        "Mix cucumbers, tomato, and chickpeas together in a salad bowl. Add lemon juice, chaat masala, and salt. Refrigerate until ready to serve."
    ],
    "image": "https://imagesvc.meredithcorp.io/v3/mm/image?q=85&c=sc&poi=face&url=https%3A%2F%2Fimages.media-allrecipes.com%2Fuserphotos%2F8412336.jpg",
    "ingredients": [
        "2  cucumbers, finely chopped",
        "1  tomato, finely chopped",
        "\u00bd cup chickpeas",
        "2 teaspoons lemon juice, or to taste",
        "1 teaspoon chaat masala",
        "salt to taste"
    ],
    "language": "en-US",
    "source": "www.allrecipes.com",
    "tags": [],
    "title": "Indian Chickpea Chaat Salad",
    "url": "https://www.allrecipes.com/recipe/266742/indian-chickpea-chaat-salad/"
}