{
    "directions": [
        "Mix flour, turmeric, baking powder, sugar, and salt in a large bowl. Mix in water until batter is thick.",
        "Heat oil in a deep-fryer or large saucepan over medium heat. Dip jackfruit in the batter and cook in batches in hot oil until golden brown, 2 to 3 minutes per side."
    ],
    "image": "https://imagesvc.meredithcorp.io/v3/mm/image?q=85&c=sc&poi=face&w=2609&h=1305&url=https%3A%2F%2Fimages.media-allrecipes.com%2Fuserphotos%2F5053609.jpg",
    "ingredients": [
        "4 cups all-purpose flour",
        "1 teaspoon ground turmeric",
        "\u00bc teaspoon baking powder",
        "1 pinch white sugar, or to taste",
        "salt to taste",
        "2 cups water",
        "oil for frying",
        "10 pieces drained jackfruit"
    ],
    "language": "en-US",
    "source": "www.allrecipes.com",
    "tags": [],
    "title": "Jackfruit Crawls",
    "url": "https://www.allrecipes.com/recipe/256661/jackfruit-crawls/"
}