{
    "directions": [
        "Preheat oven to 350 degrees F (175 degrees C).",
        "Combine millet, soy milk powder, hot water, chopped dates, coconut, and vanilla in a 9x13 inch casserole dish.",
        "Bake casserole in preheated oven for 30 minutes, then remove and stir. Return casserole to oven and bake an additional 30 minutes. Serve hot."
    ],
    "image": "https://www.allrecipes.com/img/misc/og-default.png",
    "ingredients": [
        "1 cup uncooked millet",
        "\u00bd cup soy milk powder",
        "5\u2009\u00bd cups hot water",
        "\u2154 cup chopped dates",
        "\u00bd cup flaked coconut",
        "1 teaspoon vanilla extract"
    ],
    "language": "en-US",
    "source": "www.allrecipes.com",
    "tags": [],
    "title": "Millet Delight | Allrecipes",
    "url": "https://www.allrecipes.com/recipe/18212/millet-delight/"
}