{
    "directions": [
        "Place the garlic, green bell peppers, red bell peppers, green chile peppers, and onions into a food processor, and process to a coarse puree. Spoon the sofrito into ice cube trays and freeze. Once the cubes are solidly frozen, transfer them to a resealable freezer bag. Keep frozen for use as needed."
    ],
    "image": "https://imagesvc.meredithcorp.io/v3/mm/image?q=85&c=sc&poi=face&w=700&h=350&url=https%3A%2F%2Fimages.media-allrecipes.com%2Fuserphotos%2F301061.jpg",
    "ingredients": [
        "9 cloves garlic, coarsely chopped",
        "4  green bell peppers, seeded and chopped",
        "2  red bell peppers, seeded and chopped",
        "2  green chile peppers, seeded and chopped",
        "2  onions, chopped"
    ],
    "language": "en-US",
    "source": "www.allrecipes.com",
    "tags": [],
    "title": "Puerto Rican Sofrito",
    "url": "https://www.allrecipes.com/recipe/206170/puerto-rican-sofrito/"
}