{
    "directions": [
        "Heat oil over medium-high heat in a large frying pan.  Add onions and garlic; cook and stir until soft.",
        "Mix in breadcrumbs, and cook and stir until brown.",
        "Stir in kale, and cook until wilted.  Serve hot or warm."
    ],
    "image": "https://imagesvc.meredithcorp.io/v3/mm/image?q=85&c=sc&poi=face&w=1600&h=800&url=https%3A%2F%2Fimages.media-allrecipes.com%2Fuserphotos%2F35820.jpg",
    "ingredients": [
        "3 tablespoons olive oil",
        "1  onion, chopped",
        "3 cloves garlic, minced",
        "1 cup bread crumbs",
        "3 bunches kale - washed, dried, and shredded"
    ],
    "language": "en-US",
    "source": "www.allrecipes.com",
    "tags": [],
    "title": "Stir Fried Kale",
    "url": "https://www.allrecipes.com/recipe/14091/stir-fried-kale/"
}