{
    "directions": [
        "Process ginger, turmeric, and oranges through a juicer in the order listed. Pour over ice and drink immediately."
    ],
    "image": "https://imagesvc.meredithcorp.io/v3/mm/image?q=85&c=sc&poi=face&url=https%3A%2F%2Fimages.media-allrecipes.com%2Fuserphotos%2F7855122.jpg",
    "ingredients": [
        "1 (2 inch) piece fresh ginger root",
        "2 (1 1/2 inch) pieces fresh turmeric",
        "3 large  naval oranges, peeled",
        "ice cubes"
    ],
    "language": "en-US",
    "source": "www.allrecipes.com",
    "tags": [],
    "title": "Super Immunity Boost Juice",
    "url": "https://www.allrecipes.com/recipe/279599/super-immunity-boost-juice/"
}