{
    "directions": [
        "Heat oil in a wide skillet over medium heat.",
        "Combine gram flour, cumin, cayenne pepper, turmeric, and salt in a bowl. Add 2 tablespoons of the hot oil and mix well. Add water, a little at a time, until a very thick batter forms. Stir in cilantro and spinach.",
        "Dip potatoes and cauliflower in batter and add to the hot oil in batches without crowding. Turn and fry until golden brown, 3 to 5 minutes. Add onions to remaining batter all at once; scoop onion-batter into the oil and fry until golden, 3 to 5 minutes."
    ],
    "image": "https://www.allrecipes.com/img/misc/og-default.png",
    "ingredients": [
        "vegetable oil for frying",
        "1 cup gram flour (besan)",
        "1 teaspoon ground cumin",
        "\u00bd teaspoon cayenne pepper",
        "\u215b teaspoon ground turmeric",
        "salt to taste",
        "water, or as needed",
        "2 tablespoons chopped cilantro",
        "2 tablespoons chopped fresh spinach",
        "\u00bd cup sliced potatoes",
        "\u00bd cup cauliflower florets",
        "\u00bd cup red onion, sliced lengthwise"
    ],
    "language": "en-US",
    "source": "www.allrecipes.com",
    "tags": [],
    "title": "Vegetable Pakora",
    "url": "https://www.allrecipes.com/recipe/266745/vegetable-pakora/"
}